repostruc/__init__.py
repostruc/argHandler.py
repostruc/repostruc.py
repostruc/returnUtils.py
repostruc/treeUtils.py
repostruc-0.0.6.dist-info/LICENSE
repostruc-0.0.6.dist-info/METADATA
repostruc-0.0.6.dist-info/WHEEL
repostruc-0.0.6.dist-info/entry_points.txt
repostruc-0.0.6.dist-info/top_level.txt
repostruc-0.0.6.dist-info/RECORD
