Metadata-Version: 2.1
Name: repostruc
Version: 0.0.6
Summary: Python module to generate Directory tree structure.
Home-page: https://github.com/Atharva-Gundawar/repostruc
Author: Atharva Gundawar
Author-email: atharva.n.gundawar@gmail.com
License: MIT
Keywords: Folder_structure folder structure repository directory tree python py
Platform: UNKNOWN
Classifier: License :: OSI Approved :: MIT License
Classifier: Programming Language :: Python
Classifier: Programming Language :: Python :: 3.5
Classifier: Programming Language :: Python :: 3.6
Classifier: Programming Language :: Python :: Implementation :: CPython
Classifier: Programming Language :: Python :: Implementation :: PyPy
Classifier: Operating System :: OS Independent
Requires-Python: >=3.5.0
License-File: LICENSE
Requires-Dist: pathlib
Requires-Dist: pyperclip
Requires-Dist: gitignore-parser
Requires-Dist: setuptools
Requires-Dist: docopt
